uptime_kuma_api/__init__.py
uptime_kuma_api/__version__.py
uptime_kuma_api/api.py
uptime_kuma_api/auth_method.py
uptime_kuma_api/docker_type.py
uptime_kuma_api/docstrings.py
uptime_kuma_api/event.py
uptime_kuma_api/exceptions.py
uptime_kuma_api/incident_style.py
uptime_kuma_api/maintenance_strategy.py
uptime_kuma_api/monitor_status.py
uptime_kuma_api/monitor_type.py
uptime_kuma_api/notification_providers.py
uptime_kuma_api/proxy_protocol.py
uptime_kuma_api_v2-1.0.0.dist-info/licenses/LICENSE
uptime_kuma_api_v2-1.0.0.dist-info/METADATA
uptime_kuma_api_v2-1.0.0.dist-info/WHEEL
uptime_kuma_api_v2-1.0.0.dist-info/top_level.txt
uptime_kuma_api_v2-1.0.0.dist-info/RECORD
